automagik_spark/__init__.py
automagik_spark/__main__.py
automagik_spark/version.py
automagik_spark/api/__init__.py
automagik_spark/api/app.py
automagik_spark/api/config.py
automagik_spark/api/dependencies.py
automagik_spark/api/models.py
automagik_spark/api/routers/__init__.py
automagik_spark/api/routers/schedules.py
automagik_spark/api/routers/sources.py
automagik_spark/api/routers/tasks.py
automagik_spark/api/routers/workflows.py
automagik_spark/cli/__init__.py
automagik_spark/cli/cli.py
automagik_spark/cli/commands/__init__.py
automagik_spark/cli/commands/api.py
automagik_spark/cli/commands/db.py
automagik_spark/cli/commands/schedule.py
automagik_spark/cli/commands/source.py
automagik_spark/cli/commands/task.py
automagik_spark/cli/commands/worker.py
automagik_spark/cli/commands/workflow.py
automagik_spark/cli/utils/__init__.py
automagik_spark/cli/utils/async_helper.py
automagik_spark/cli/utils/log.py
automagik_spark/cli/utils/table_styles.py
automagik_spark/core/__init__.py
automagik_spark/core/celery_config.py
automagik_spark/core/config.py
automagik_spark/core/workflow_runner.py
automagik_spark/core/celery/__init__.py
automagik_spark/core/celery/celery_app.py
automagik_spark/core/celery/scheduler.py
automagik_spark/core/celery/tasks.py
automagik_spark/core/database/__init__.py
automagik_spark/core/database/base.py
automagik_spark/core/database/models.py
automagik_spark/core/database/session.py
automagik_spark/core/scheduler/__init__.py
automagik_spark/core/scheduler/manager.py
automagik_spark/core/scheduler/scheduler.py
automagik_spark/core/scheduler/task_runner.py
automagik_spark/core/tasks/__init__.py
automagik_spark/core/tasks/celery.py
automagik_spark/core/tasks/workflow_tasks.py
automagik_spark/core/workflows/__init__.py
automagik_spark/core/workflows/analyzer.py
automagik_spark/core/workflows/automagik_agents.py
automagik_spark/core/workflows/manager.py
automagik_spark/core/workflows/remote.py
automagik_spark/core/workflows/source.py
automagik_spark-0.3.2.dist-info/licenses/LICENSE
automagik_spark-0.3.2.dist-info/METADATA
automagik_spark-0.3.2.dist-info/WHEEL
automagik_spark-0.3.2.dist-info/entry_points.txt
automagik_spark-0.3.2.dist-info/top_level.txt
automagik_spark-0.3.2.dist-info/RECORD
