Metadata-Version: 2.4
Name: automagik-spark
Version: 0.3.2
Summary: AutoMagik Spark - Automagion Engine with LangFlow integration
Home-page: https://github.com/namastexlabs/automagik-spark
Author: NamasteX Labs
Author-email: NamasteX Labs <support@namastexlabs.com>
License-Expression: MIT
Project-URL: Bug Tracker, https://github.com/namastexlabs/automagik-spark/issues
Project-URL: Documentation, https://github.com/namastexlabs/automagik-spark/tree/main/docs
Project-URL: Homepage, https://github.com/namastexlabs/automagik-spark
Project-URL: Repository, https://github.com/namastexlabs/automagik-spark
Keywords: automation,workflow,langflow,ai,llm
Classifier: Development Status :: 4 - Beta
Classifier: Environment :: Console
Classifier: Intended Audience :: Developers
Classifier: Operating System :: OS Independent
Classifier: Programming Language :: Python :: 3
Classifier: Programming Language :: Python :: 3.10
Classifier: Programming Language :: Python :: 3.11
Classifier: Topic :: Software Development :: Libraries :: Python Modules
Classifier: Topic :: System :: Systems Administration
Requires-Python: >=3.9
License-File: LICENSE
Requires-Dist: click
Requires-Dist: alembic
Requires-Dist: sqlalchemy
Requires-Dist: psycopg2-binary
Requires-Dist: redis
Requires-Dist: aiohttp
Requires-Dist: pydantic
Requires-Dist: python-dotenv
Requires-Dist: pytz
Requires-Dist: croniter
Requires-Dist: httpx
Requires-Dist: tabulate
Requires-Dist: setuptools
Requires-Dist: asyncpg>=0.30.0
Requires-Dist: fastapi>=0.109.0
Requires-Dist: uvicorn[standard]>=0.27.0
Requires-Dist: psutil
Requires-Dist: rich
Requires-Dist: cryptography>=44.0.0
Requires-Dist: pytest>=8.3.4
Requires-Dist: aiosqlite>=0.20.0
Requires-Dist: pytest-asyncio>=0.25.3
Requires-Dist: pytest-mock>=3.14.0
Requires-Dist: celery>=5.4.0
Requires-Dist: tenacity>=9.0.0
Provides-Extra: dev
Requires-Dist: pytest>=8.3.4; extra == "dev"
Requires-Dist: pytest-asyncio>=0.23.5; extra == "dev"
Requires-Dist: pytest-cov>=6.0.0; extra == "dev"
Requires-Dist: aiosqlite>=0.19.0; extra == "dev"
Requires-Dist: ruff>=0.1.0; extra == "dev"
Requires-Dist: black>=23.0.0; extra == "dev"
Requires-Dist: mypy>=1.5.0; extra == "dev"
Dynamic: author
Dynamic: home-page
Dynamic: license-file
Dynamic: requires-python
